{"ver":"1.1.0","updated":1700850911645,"forumID":"1010195","tournamentID":41,"url":"https://osu.ppy.sh/community/forums/topics/1010195","postedDate":1578941702000,"postedBy":{"id":"3328606","name":"Redavor"},"cover":"https://assets.ppy.sh/topic-covers/5344/74665bcd89389ab19a1b08ebe858a368337e6fea8b528d2f293ae6fa009e3f6a.png","name":"Rapid Monthly osu! Tournament #41 1v1 30k-70k","banner":"https://i.ppy.sh/d62a9d81e7d6caa3c828bf17cafba1a41646ff41/68747470733a2f2f696d6775722d617263686976652e7070792e73682f4e636479546f432e706e67","ranks":{"high":30000,"low":70000,"buffer":2000},"links":{"discord":"https://discord.gg/9sKe7nF","twitch":"https://www.twitch.tv/rapid_tournaments","challonge":"http://challonge.com/rmosutourney41"},"schedule":{"regStart":1578873600000,"regEnd":1579903200000,"playPreStart":1579963800000,"playStart":1579964400000},"pool":{"nm":[{"id":"380475","set":"155034","deleted":false,"pickedBy":"Lefafel","modSlot":"nm","modEnum":0},{"id":"2195244","set":"1050382","deleted":false,"pickedBy":"Lefafel","modSlot":"nm","modEnum":0},{"id":"2124036","set":"1008607","deleted":false,"pickedBy":"nik","modSlot":"nm","modEnum":0}],"hd":[{"id":"2226615","set":"1059539","deleted":false,"pickedBy":"Meow Mix","modSlot":"hd","modEnum":8}],"hr":[{"id":"980637","set":"457621","deleted":false,"pickedBy":"Redavor","modSlot":"hr","modEnum":16}],"dt":[{"id":"335436","set":"123078","deleted":false,"pickedBy":"Meow Mix","modSlot":"dt","modEnum":64}],"fm":[{"id":"2103163","set":"941053","deleted":false,"pickedBy":"Lefafel","modSlot":"fm","modEnum":0},{"id":"2148398","set":"1027359","deleted":false,"pickedBy":"Lefafel","modSlot":"fm","modEnum":0}],"tb":[{"id":"437671","set":"182520","deleted":false,"pickedBy":"nik","modSlot":"tb","modEnum":0}]}}
