{"ver":"1.0.0","updated":1700798584461,"pool":{"nm":[{"beatmapset_id":"376545","beatmap_id":"824359","approved":"1","total_length":"135","hit_length":"130","version":"Extra","file_md5":"3fddd4bcac0f6a41f3f46ccda4ce45e6","diff_size":"4.2","diff_overall":"8.2","diff_approach":"9.4","diff_drain":"6","mode":"0","count_normal":"277","count_slider":"296","count_spinner":"2","submit_date":"2015-11-14 06:40:29","approved_date":"2015-12-04 10:40:12","last_update":"2015-11-26 04:44:18","artist":"Streetlight Manifesto","artist_unicode":"Streetlight Manifesto","title":"The Blonde Lead The Blind","title_unicode":"The Blonde Lead The Blind","creator":"pishifat","creator_id":"3178418","bpm":"276","source":"","tags":"somewhere in the inbetween jazz ska","genre_id":"5","language_id":"2","favourite_count":"122","rating":"9.20195","storyboard":"0","video":"0","download_unavailable":"0","audio_unavailable":"0","playcount":"70625","passcount":"16312","packs":"S448","max_combo":"908","diff_aim":"2.63688","diff_speed":"2.58371","difficultyrating":"5.45432","updated_at":1700798584709,"picked_by":"Lefafel","was_set_link":false},{"beatmapset_id":"665179","beatmap_id":"1407818","approved":"1","total_length":"227","hit_length":"202","version":"Re:Union","file_md5":"4242ade1fdb5bc6df8440b498a1f2e3b","diff_size":"4","diff_overall":"9","diff_approach":"9.3","diff_drain":"6","mode":"0","count_normal":"492","count_slider":"302","count_spinner":"4","submit_date":"2017-09-06 02:11:06","approved_date":"2018-01-03 12:20:16","last_update":"2017-12-25 12:47:22","artist":"sweet ARMS","artist_unicode":"sweet ARMS","title":"Key of Truth","title_unicode":"Key of Truth","creator":"sahuang","creator_id":"5318910","bpm":"192","source":"デート・ア・ライブTwin Edition凜緒リンカーネイション","tags":"date a live twin edition rio reincarnation game opening theme song ps vita kawaiwkyik rizia wkyik gaia my angel azusa celsiuslk","genre_id":"2","language_id":"3","favourite_count":"353","rating":"9.442","storyboard":"0","video":"0","download_unavailable":"0","audio_unavailable":"0","playcount":"142461","passcount":"13680","packs":"S602","max_combo":"1139","diff_aim":"3.01487","diff_speed":"2.51352","difficultyrating":"5.8303","updated_at":1700798586255,"picked_by":"Lefafel","was_set_link":false},{"beatmapset_id":"769346","beatmap_id":"2839573","approved":"1","total_length":"249","hit_length":"235","version":"-Kemsyt's Insane","file_md5":"39f1d25ea5c76ba865e45e40ab85f8f1","diff_size":"4","diff_overall":"8.3","diff_approach":"9.2","diff_drain":"5.2","mode":"0","count_normal":"670","count_slider":"430","count_spinner":"0","submit_date":"2018-04-22 19:17:23","approved_date":"2022-05-24 18:45:51","last_update":"2022-05-04 18:07:51","artist":"Whispered","artist_unicode":"Whispered","title":"Exile of the Floating World","title_unicode":"Exile of the Floating World","creator":"MrKosiej","creator_id":"7024544","bpm":"225","source":"","tags":"metal japanese metsutan songs of the void english blood9 saltylucario thekinghenry -kemsyt gabdu09 saltking salty melodic death melodeath folk oriental japanese","genre_id":"11","language_id":"2","favourite_count":"301","rating":"9.65992","storyboard":"1","video":"0","download_unavailable":"0","audio_unavailable":"0","playcount":"59635","passcount":"13130","packs":"S1179","max_combo":"1820","diff_aim":"2.54798","diff_speed":"2.6778","difficultyrating":"5.46302","updated_at":1700798587791,"picked_by":"Lefafel","was_set_link":false}],"hd":[{"beatmapset_id":"1749750","beatmap_id":"3580554","approved":"1","total_length":"141","hit_length":"134","version":"Extra","file_md5":"7cd381787bdb1765b545472413d1244e","diff_size":"4","diff_overall":"9","diff_approach":"9.2","diff_drain":"5","mode":"0","count_normal":"398","count_slider":"198","count_spinner":"1","submit_date":"2022-04-24 10:48:57","approved_date":"2022-05-28 21:24:19","last_update":"2022-05-22 16:24:26","artist":"Gabry Ponte, LUM!X, Prezioso","artist_unicode":"Gabry Ponte, LUM!X, Prezioso","title":"Thunder (Nightcore Mix)","title_unicode":"Thunder (Nightcore Mix)","creator":"P A N","creator_id":"1285234","bpm":"148.5","source":"","tags":"simple- english en electronic dance music edm nightcore nc trance techno p_a_n","genre_id":"10","language_id":"2","favourite_count":"2181","rating":"9.35862","storyboard":"0","video":"0","download_unavailable":"0","audio_unavailable":"0","playcount":"365599","passcount":"53039","packs":"S1181","max_combo":"817","diff_aim":"2.84329","diff_speed":"2.38301","difficultyrating":"5.50884","updated_at":1700798589333,"picked_by":"Lefafel","was_set_link":false},{"beatmapset_id":"1640622","beatmap_id":"3356349","approved":"1","total_length":"126","hit_length":"125","version":"PandaHero's Insane","file_md5":"448aecb4b5903308dc162b3cd561df04","diff_size":"4","diff_overall":"7","diff_approach":"8","diff_drain":"6","mode":"0","count_normal":"437","count_slider":"141","count_spinner":"0","submit_date":"2021-12-01 07:45:35","approved_date":"2022-02-11 07:42:06","last_update":"2022-02-01 00:23:13","artist":"Leo/need","artist_unicode":"Leo/need","title":"Asu no Yozora Shoukaihan","title_unicode":"アスノヨゾラ哨戒班","creator":"LiSAKOU","creator_id":"13946454","bpm":"185","source":"プロジェクトセカイ カラフルステージ！ feat. 初音ミク","tags":"orangestar pandahero ponbot 星乃一歌 hoshino ichika vocaloid video game project sekai colorful stage rockwell ia night sky patrol of tomorrow japanese pop jpop","genre_id":"5","language_id":"3","favourite_count":"288","rating":"8.26966","storyboard":"0","video":"0","download_unavailable":"0","audio_unavailable":"0","playcount":"34696","passcount":"1496","packs":"S1137","max_combo":"746","diff_aim":"2.34841","diff_speed":"2.55678","difficultyrating":"5.13503","updated_at":1700798590874,"picked_by":"Lefafel","was_set_link":false}],"hr":[{"beatmapset_id":"24918","beatmap_id":"84538","approved":"1","total_length":"139","hit_length":"123","version":"Insane","file_md5":"435c83b49a34ebe05d8780297b260fd1","diff_size":"4","diff_overall":"7","diff_approach":"8","diff_drain":"6","mode":"0","count_normal":"378","count_slider":"102","count_spinner":"1","submit_date":"2011-01-16 23:44:48","approved_date":"2011-05-27 01:06:39","last_update":"2011-05-27 00:59:49","artist":"Groove Coverage","artist_unicode":null,"title":"The End (Nightcore Remix)","title_unicode":null,"creator":"winber1","creator_id":"270328","bpm":"183.29","source":"","tags":"","genre_id":"10","language_id":"2","favourite_count":"309","rating":"9.25768","storyboard":"1","video":"0","download_unavailable":"0","audio_unavailable":"0","playcount":"506810","passcount":"38550","packs":"S187,T43","max_combo":"695","diff_aim":"2.83352","diff_speed":"2.50691","difficultyrating":"5.60321","updated_at":1700798592430,"picked_by":"zts","was_set_link":false},{"beatmapset_id":"1742131","beatmap_id":"3562042","approved":"1","total_length":"110","hit_length":"109","version":"Lunatic","file_md5":"63d00b769dc3f7c4298fe9520dcb41fc","diff_size":"4","diff_overall":"8","diff_approach":"9","diff_drain":"4","mode":"0","count_normal":"396","count_slider":"173","count_spinner":"1","submit_date":"2022-04-14 14:22:40","approved_date":"2022-06-15 19:02:00","last_update":"2022-06-10 16:06:12","artist":"tsunamix_underground","artist_unicode":"tsunamix_underground","title":"Period. ~ Seishin no Kousoku to Jiyuu o Tsukamu Jouka (Cut Ver.)","title_unicode":"Period. ～ 精神ノ拘束ト自由ヲ掴ム浄化 (Cut Ver.)","creator":"Skubi","creator_id":"3687666","bpm":"150","source":"東方Project","tags":"touhou celestian c-clays 天空のグリニッジ 水斎 -prism- greenwich in the sky usami renko maribel hearn han team shanghai alice zun 大空魔術　～ magical astronomy 上海アリス幻樂団 techno suisai c82 comic market comiket コミックマーケット82 コミケット マエリベリー・ハーン 宇佐見蓮子 k2 sound haan celestial wizardry oozora majutsu electronic instrumental video game cptsqbany chanmann","genre_id":"10","language_id":"5","favourite_count":"203","rating":"9.35165","storyboard":"0","video":"0","download_unavailable":"0","audio_unavailable":"0","playcount":"30565","passcount":"8872","packs":"S1189","max_combo":"779","diff_aim":"2.60933","diff_speed":"2.63897","difficultyrating":"5.48281","updated_at":1700798593994,"picked_by":"Lefafel","was_set_link":false}],"dt":[{"beatmapset_id":"109446","beatmap_id":"373657","approved":"1","total_length":"193","hit_length":"167","version":"Luanny's Insane","file_md5":"462eb487d13f853d6904e8c67f8c0207","diff_size":"6","diff_overall":"6","diff_approach":"8","diff_drain":"5","mode":"0","count_normal":"211","count_slider":"257","count_spinner":"2","submit_date":"2013-08-07 01:57:32","approved_date":"2014-03-05 18:02:40","last_update":"2014-02-26 06:18:29","artist":"Enya","artist_unicode":"Enya","title":"Caribbean Blue","title_unicode":"Caribbean Blue","creator":"Blue Dragon","creator_id":"19048","bpm":"157.63","source":"","tags":"shepherd moons new age luanny","genre_id":"6","language_id":"2","favourite_count":"142","rating":"9.20843","storyboard":"1","video":"0","download_unavailable":"0","audio_unavailable":"0","playcount":"92176","passcount":"18751","packs":"S346,TC14","max_combo":"861","diff_aim":"2.96298","diff_speed":"2.31276","difficultyrating":"5.60762","updated_at":1700798595544,"picked_by":"Lefafel","was_set_link":false},{"beatmapset_id":"237854","beatmap_id":"628995","approved":"1","total_length":"197","hit_length":"179","version":"Hyper","file_md5":"40d1f045fd6deb0d7b24c21735f51285","diff_size":"4","diff_overall":"6","diff_approach":"8","diff_drain":"5","mode":"0","count_normal":"136","count_slider":"378","count_spinner":"2","submit_date":"2014-11-29 02:08:08","approved_date":"2016-01-24 21:01:04","last_update":"2016-01-16 17:35:45","artist":"Jeff Williams","artist_unicode":"Jeff Williams","title":"Time to say Goodbye (feat. Casey Lee Williams)","title_unicode":"Time to say Goodbye (feat. Casey Lee Williams)","creator":"Pho","creator_id":"3624692","bpm":"250","source":"RWBY","tags":"rwby volume 2 opening full ver appleeaterx super kawaii milan- mao okoratu","genre_id":"3","language_id":"2","favourite_count":"2236","rating":"9.37654","storyboard":"1","video":"0","download_unavailable":"0","audio_unavailable":"0","playcount":"608984","passcount":"75985","packs":"S457","max_combo":"1073","diff_aim":"2.81313","diff_speed":"2.44242","difficultyrating":"5.52204","updated_at":1700798597094,"picked_by":"zts","was_set_link":false}],"tb":[{"beatmapset_id":"133693","beatmap_id":"335628","approved":"1","total_length":"428","hit_length":"378","version":"Extra Stage","file_md5":"017d33f07427799d0fc01777d7e177a3","diff_size":"4","diff_overall":"9","diff_approach":"9","diff_drain":"7","mode":"0","count_normal":"1599","count_slider":"469","count_spinner":"3","submit_date":"2013-12-10 03:36:36","approved_date":"2014-07-22 04:02:15","last_update":"2014-07-15 03:35:48","artist":"Demetori","artist_unicode":"Demetori","title":"Kanjou no Matenrou ~ World's End","title_unicode":"感情の魔天楼　～ World's End","creator":"GoldenWolf","creator_id":"1612624","bpm":"178","source":"Touhou","tags":"emotional skyscraper cosmic mind 曼衍珠汝華 manenjushaka nada upasana pundarika byakuren hijiri undefined fantastic object th12 woof","genre_id":"11","language_id":"5","favourite_count":"1124","rating":"9.70221","storyboard":"0","video":"0","download_unavailable":"0","audio_unavailable":"0","playcount":"2540376","passcount":"112536","packs":"A18,SA15","max_combo":"2780","diff_aim":"2.77023","diff_speed":"2.89628","difficultyrating":"5.92292","updated_at":1700798598638,"picked_by":"Lefafel","was_set_link":false}]}}
